jshmodule2/__init__.py
jshmodule2/address_converter.py
jshmodule2/data/HangJeongDong_ver20230701.geojson
jshmodule2/data/emd.dbf
jshmodule2/data/emd.prj
jshmodule2/data/emd.shp
jshmodule2/data/emd.shx
jshmodule2-1.1.3.dist-info/METADATA
jshmodule2-1.1.3.dist-info/WHEEL
jshmodule2-1.1.3.dist-info/top_level.txt
jshmodule2-1.1.3.dist-info/RECORD
