Metadata-Version: 2.1
Name: jshmodule2
Version: 1.1.3
Summary: UNKNOWN
Home-page: UNKNOWN
License: UNKNOWN
Platform: UNKNOWN
Requires-Dist: geopandas
Requires-Dist: shapely
Requires-Dist: requests
Requires-Dist: pyproj
